{
  "generated_at": "2026-06-12T21:03:15.820636+08:00",
  "total_scanned": 26995,
  "sp500": {
    "series": 7,
    "funds": 25
  },
  "nasdaq_passive": {
    "series": 17,
    "funds": 60
  },
  "active": {
    "series": 20,
    "funds": 57
  },
  "global_index": {
    "series": 2,
    "funds": 5
  },
  "global_other": {
    "series": 23,
    "funds": 68
  },
  "etf": {
    "series": 18,
    "funds": 18
  },
  "excluded_count": 26762,
  "purchase_refreshed_at": "2026-06-12T21:03:15.820365+08:00"
}
