{
  "generated_at": "2026-05-30T13:19:08.702328",
  "total_scanned": 26906,
  "sp500": {
    "series": 7,
    "funds": 25
  },
  "nasdaq_passive": {
    "series": 17,
    "funds": 60
  },
  "active": {
    "series": 19,
    "funds": 53
  },
  "global_index": {
    "series": 2,
    "funds": 5
  },
  "global_other": {
    "series": 24,
    "funds": 72
  },
  "etf": {
    "series": 18,
    "funds": 18
  },
  "excluded_count": 26673,
  "enriched_at": "2026-05-30T13:26:01.262916",
  "enriched_fields": [
    "涨跌幅",
    "规模",
    "限额",
    "基金经理",
    "成立时间"
  ],
  "purchase_refreshed_at": "2026-06-01T21:06:56.070155"
}